riya_first_demopackage123/__init__.py
riya_first_demopackage123/helper.py
riya_first_demopackage123-0.1.0.dist-info/LICENSE
riya_first_demopackage123-0.1.0.dist-info/METADATA
riya_first_demopackage123-0.1.0.dist-info/WHEEL
riya_first_demopackage123-0.1.0.dist-info/top_level.txt
riya_first_demopackage123-0.1.0.dist-info/RECORD
